<?xml version="1.0" encoding="UTF-8"?>
<DEFECTS>
  <DEFECT>
    <SFA>
      <FILEPATH>D:\Yolo_v4\darknet\src\</FILEPATH>
      <FILENAME>activations.h</FILENAME>
      <LINE>72</LINE>
      <COLUMN>62</COLUMN>
    </SFA>
    <DEFECTCODE>26451</DEFECTCODE>
    <DESCRIPTION>산술 오버플로: 4 바이트 값의 '+' 연산자를 사용한 다음 결과를 8 바이트 값에 캐스트합니다. 오버플로를 방지하려면 '+' 연산자를 호출하기 전에 더 광범위한 형식에 값을 캐스트합니다(io.2).</DESCRIPTION>
    <FUNCTION>gelu_activate</FUNCTION>
    <DECORATED>gelu_activate</DECORATED>
    <FUNCLINE>72</FUNCLINE>
    <PATH></PATH>
  </DEFECT>
  <DEFECT>
    <SFA>
      <FILEPATH>D:\Yolo_v4\darknet\src\</FILEPATH>
      <FILENAME>coco.c</FILENAME>
      <LINE>163</LINE>
      <COLUMN>43</COLUMN>
    </SFA>
    <DEFECTCODE>26451</DEFECTCODE>
    <DESCRIPTION>산술 오버플로: 4 바이트 값의 '*' 연산자를 사용한 다음 결과를 8 바이트 값에 캐스트합니다. 오버플로를 방지하려면 '*' 연산자를 호출하기 전에 더 광범위한 형식에 값을 캐스트합니다(io.2).</DESCRIPTION>
    <FUNCTION>validate_coco</FUNCTION>
    <DECORATED>validate_coco</DECORATED>
    <FUNCLINE>137</FUNCLINE>
    <PATH></PATH>
  </DEFECT>
  <DEFECT>
    <SFA>
      <FILEPATH>D:\Yolo_v4\darknet\src\</FILEPATH>
      <FILENAME>coco.c</FILENAME>
      <LINE>163</LINE>
      <COLUMN>36</COLUMN>
    </SFA>
    <DEFECTCODE>26451</DEFECTCODE>
    <DESCRIPTION>산술 오버플로: 4 바이트 값의 '*' 연산자를 사용한 다음 결과를 8 바이트 값에 캐스트합니다. 오버플로를 방지하려면 '*' 연산자를 호출하기 전에 더 광범위한 형식에 값을 캐스트합니다(io.2).</DESCRIPTION>
    <FUNCTION>validate_coco</FUNCTION>
    <DECORATED>validate_coco</DECORATED>
    <FUNCLINE>137</FUNCLINE>
    <PATH></PATH>
  </DEFECT>
  <DEFECT>
    <SFA>
      <FILEPATH>D:\Yolo_v4\darknet\src\</FILEPATH>
      <FILENAME>coco.c</FILENAME>
      <LINE>164</LINE>
      <COLUMN>49</COLUMN>
    </SFA>
    <DEFECTCODE>26451</DEFECTCODE>
    <DESCRIPTION>산술 오버플로: 4 바이트 값의 '*' 연산자를 사용한 다음 결과를 8 바이트 값에 캐스트합니다. 오버플로를 방지하려면 '*' 연산자를 호출하기 전에 더 광범위한 형식에 값을 캐스트합니다(io.2).</DESCRIPTION>
    <FUNCTION>validate_coco</FUNCTION>
    <DECORATED>validate_coco</DECORATED>
    <FUNCLINE>137</FUNCLINE>
    <PATH></PATH>
  </DEFECT>
  <DEFECT>
    <SFA>
      <FILEPATH>D:\Yolo_v4\darknet\src\</FILEPATH>
      <FILENAME>coco.c</FILENAME>
      <LINE>164</LINE>
      <COLUMN>42</COLUMN>
    </SFA>
    <DEFECTCODE>26451</DEFECTCODE>
    <DESCRIPTION>산술 오버플로: 4 바이트 값의 '*' 연산자를 사용한 다음 결과를 8 바이트 값에 캐스트합니다. 오버플로를 방지하려면 '*' 연산자를 호출하기 전에 더 광범위한 형식에 값을 캐스트합니다(io.2).</DESCRIPTION>
    <FUNCTION>validate_coco</FUNCTION>
    <DECORATED>validate_coco</DECORATED>
    <FUNCLINE>137</FUNCLINE>
    <PATH></PATH>
  </DEFECT>
  <DEFECT>
    <SFA>
      <FILEPATH>D:\Yolo_v4\darknet\src\</FILEPATH>
      <FILENAME>coco.c</FILENAME>
      <LINE>265</LINE>
      <COLUMN>43</COLUMN>
    </SFA>
    <DEFECTCODE>26451</DEFECTCODE>
    <DESCRIPTION>산술 오버플로: 4 바이트 값의 '*' 연산자를 사용한 다음 결과를 8 바이트 값에 캐스트합니다. 오버플로를 방지하려면 '*' 연산자를 호출하기 전에 더 광범위한 형식에 값을 캐스트합니다(io.2).</DESCRIPTION>
    <FUNCTION>validate_coco_recall</FUNCTION>
    <DECORATED>validate_coco_recall</DECORATED>
    <FUNCLINE>238</FUNCLINE>
    <PATH></PATH>
  </DEFECT>
  <DEFECT>
    <SFA>
      <FILEPATH>D:\Yolo_v4\darknet\src\</FILEPATH>
      <FILENAME>coco.c</FILENAME>
      <LINE>265</LINE>
      <COLUMN>36</COLUMN>
    </SFA>
    <DEFECTCODE>26451</DEFECTCODE>
    <DESCRIPTION>산술 오버플로: 4 바이트 값의 '*' 연산자를 사용한 다음 결과를 8 바이트 값에 캐스트합니다. 오버플로를 방지하려면 '*' 연산자를 호출하기 전에 더 광범위한 형식에 값을 캐스트합니다(io.2).</DESCRIPTION>
    <FUNCTION>validate_coco_recall</FUNCTION>
    <DECORATED>validate_coco_recall</DECORATED>
    <FUNCLINE>238</FUNCLINE>
    <PATH></PATH>
  </DEFECT>
  <DEFECT>
    <SFA>
      <FILEPATH>D:\Yolo_v4\darknet\src\</FILEPATH>
      <FILENAME>coco.c</FILENAME>
      <LINE>266</LINE>
      <COLUMN>49</COLUMN>
    </SFA>
    <DEFECTCODE>26451</DEFECTCODE>
    <DESCRIPTION>산술 오버플로: 4 바이트 값의 '*' 연산자를 사용한 다음 결과를 8 바이트 값에 캐스트합니다. 오버플로를 방지하려면 '*' 연산자를 호출하기 전에 더 광범위한 형식에 값을 캐스트합니다(io.2).</DESCRIPTION>
    <FUNCTION>validate_coco_recall</FUNCTION>
    <DECORATED>validate_coco_recall</DECORATED>
    <FUNCLINE>238</FUNCLINE>
    <PATH></PATH>
  </DEFECT>
  <DEFECT>
    <SFA>
      <FILEPATH>D:\Yolo_v4\darknet\src\</FILEPATH>
      <FILENAME>coco.c</FILENAME>
      <LINE>266</LINE>
      <COLUMN>42</COLUMN>
    </SFA>
    <DEFECTCODE>26451</DEFECTCODE>
    <DESCRIPTION>산술 오버플로: 4 바이트 값의 '*' 연산자를 사용한 다음 결과를 8 바이트 값에 캐스트합니다. 오버플로를 방지하려면 '*' 연산자를 호출하기 전에 더 광범위한 형식에 값을 캐스트합니다(io.2).</DESCRIPTION>
    <FUNCTION>validate_coco_recall</FUNCTION>
    <DECORATED>validate_coco_recall</DECORATED>
    <FUNCLINE>238</FUNCLINE>
    <PATH></PATH>
  </DEFECT>
  <DEFECT>
    <SFA>
      <FILEPATH>D:\Yolo_v4\darknet\src\</FILEPATH>
      <FILENAME>coco.c</FILENAME>
      <LINE>361</LINE>
      <COLUMN>18</COLUMN>
    </SFA>
    <DEFECTCODE>6031</DEFECTCODE>
    <DESCRIPTION>반환 값이 무시되었습니다. 'strtok'.</DESCRIPTION>
    <FUNCTION>test_coco</FUNCTION>
    <DECORATED>test_coco</DECORATED>
    <FUNCLINE>333</FUNCLINE>
    <PATH></PATH>
  </DEFECT>
  <DEFECT>
    <SFA>
      <FILEPATH>D:\Yolo_v4\darknet\src\</FILEPATH>
      <FILENAME>coco.c</FILENAME>
      <LINE>348</LINE>
      <COLUMN>47</COLUMN>
    </SFA>
    <DEFECTCODE>26451</DEFECTCODE>
    <DESCRIPTION>산술 오버플로: 4 바이트 값의 '*' 연산자를 사용한 다음 결과를 8 바이트 값에 캐스트합니다. 오버플로를 방지하려면 '*' 연산자를 호출하기 전에 더 광범위한 형식에 값을 캐스트합니다(io.2).</DESCRIPTION>
    <FUNCTION>test_coco</FUNCTION>
    <DECORATED>test_coco</DECORATED>
    <FUNCLINE>333</FUNCLINE>
    <PATH></PATH>
  </DEFECT>
  <DEFECT>
    <SFA>
      <FILEPATH>D:\Yolo_v4\darknet\src\</FILEPATH>
      <FILENAME>coco.c</FILENAME>
      <LINE>348</LINE>
      <COLUMN>38</COLUMN>
    </SFA>
    <DEFECTCODE>26451</DEFECTCODE>
    <DESCRIPTION>산술 오버플로: 4 바이트 값의 '*' 연산자를 사용한 다음 결과를 8 바이트 값에 캐스트합니다. 오버플로를 방지하려면 '*' 연산자를 호출하기 전에 더 광범위한 형식에 값을 캐스트합니다(io.2).</DESCRIPTION>
    <FUNCTION>test_coco</FUNCTION>
    <DECORATED>test_coco</DECORATED>
    <FUNCLINE>333</FUNCLINE>
    <PATH></PATH>
  </DEFECT>
  <DEFECT>
    <SFA>
      <FILEPATH>D:\Yolo_v4\darknet\src\</FILEPATH>
      <FILENAME>coco.c</FILENAME>
      <LINE>349</LINE>
      <COLUMN>53</COLUMN>
    </SFA>
    <DEFECTCODE>26451</DEFECTCODE>
    <DESCRIPTION>산술 오버플로: 4 바이트 값의 '*' 연산자를 사용한 다음 결과를 8 바이트 값에 캐스트합니다. 오버플로를 방지하려면 '*' 연산자를 호출하기 전에 더 광범위한 형식에 값을 캐스트합니다(io.2).</DESCRIPTION>
    <FUNCTION>test_coco</FUNCTION>
    <DECORATED>test_coco</DECORATED>
    <FUNCLINE>333</FUNCLINE>
    <PATH></PATH>
  </DEFECT>
  <DEFECT>
    <SFA>
      <FILEPATH>D:\Yolo_v4\darknet\src\</FILEPATH>
      <FILENAME>coco.c</FILENAME>
      <LINE>349</LINE>
      <COLUMN>44</COLUMN>
    </SFA>
    <DEFECTCODE>26451</DEFECTCODE>
    <DESCRIPTION>산술 오버플로: 4 바이트 값의 '*' 연산자를 사용한 다음 결과를 8 바이트 값에 캐스트합니다. 오버플로를 방지하려면 '*' 연산자를 호출하기 전에 더 광범위한 형식에 값을 캐스트합니다(io.2).</DESCRIPTION>
    <FUNCTION>test_coco</FUNCTION>
    <DECORATED>test_coco</DECORATED>
    <FUNCLINE>333</FUNCLINE>
    <PATH></PATH>
  </DEFECT>
</DEFECTS>